pyhostprep/__init__.py
pyhostprep/bundlemgr.py
pyhostprep/bundles.py
pyhostprep/certificates.py
pyhostprep/cli.py
pyhostprep/command.py
pyhostprep/constants.py
pyhostprep/data/config/91-couchbase.conf
pyhostprep/data/config/disable-thp
pyhostprep/data/config/packages.json
pyhostprep/data/config/sync_gateway_2.json
pyhostprep/data/config/sync_gateway_3.json
pyhostprep/data/config/sync_gateway_ssl.json
pyhostprep/data/config/tuned.conf
pyhostprep/data/playbooks/aws_cli.yaml
pyhostprep/data/playbooks/az_cli_apt.yaml
pyhostprep/data/playbooks/az_cli_dnf.yaml
pyhostprep/data/playbooks/base_sw_amzn.yaml
pyhostprep/data/playbooks/base_sw_apt.yaml
pyhostprep/data/playbooks/base_sw_yum.yaml
pyhostprep/data/playbooks/base_sw_zypper.yaml
pyhostprep/data/playbooks/configure_cbdata.yaml
pyhostprep/data/playbooks/configure_data_mnt.yaml
pyhostprep/data/playbooks/configure_swap.yaml
pyhostprep/data/playbooks/configure_swappiness.yaml
pyhostprep/data/playbooks/disable_firewall_dep.yaml
pyhostprep/data/playbooks/disable_firewalld_rhel.yaml
pyhostprep/data/playbooks/disable_thp_amzn.yaml
pyhostprep/data/playbooks/disable_thp_deb.yaml
pyhostprep/data/playbooks/disable_thp_rhel.yaml
pyhostprep/data/playbooks/disable_thp_sles.yaml
pyhostprep/data/playbooks/enable_chrony_dep.yaml
pyhostprep/data/playbooks/enable_chrony_rhel.yaml
pyhostprep/data/playbooks/enable_sgw.yaml
pyhostprep/data/playbooks/gcp_cli_apt.yaml
pyhostprep/data/playbooks/gcp_cli_dnf.yaml
pyhostprep/data/playbooks/install_cbs_apt.yaml
pyhostprep/data/playbooks/install_cbs_sles.yaml
pyhostprep/data/playbooks/install_cbs_yum.yaml
pyhostprep/data/playbooks/install_libcouchbase_apt.yaml
pyhostprep/data/playbooks/install_libcouchbase_yum.yaml
pyhostprep/data/playbooks/install_sgw_deb.yaml
pyhostprep/data/playbooks/install_sgw_rpm.yaml
pyhostprep/ebsnvme.py
pyhostprep/exception.py
pyhostprep/gateway.py
pyhostprep/hostinfo.py
pyhostprep/httpsessionmgr.py
pyhostprep/network.py
pyhostprep/osfamily.py
pyhostprep/osinfo.py
pyhostprep-1.0.59.dist-info/LICENSE.txt
pyhostprep-1.0.59.dist-info/METADATA
pyhostprep-1.0.59.dist-info/WHEEL
pyhostprep-1.0.59.dist-info/entry_points.txt
pyhostprep-1.0.59.dist-info/RECORD
